nlabapi-1.0.5.dist-info/METADATA
nlabapi-1.0.5.dist-info/WHEEL
nlabapi-1.0.5.dist-info/entry_points.txt
nlabapi-1.0.5.dist-info/licenses/LICENSE
nlabapi.libs/libattr-f90bb31a.so.1
nlabapi.libs/libbz2-58d7711f.so.1
nlabapi.libs/libcap-a78d9113.so.2
nlabapi.libs/libdw-59e5ce70.so.1
nlabapi.libs/libelf-ab5eae85.so.1
nlabapi.libs/liblzma-11b66597.so.5
nlabapi.libs/libudev-2013d2bb.so.1
nlabapi/__init__.py
nlabapi/nlabapi.cpython-312-i386-linux-gnu.so
nlabapi-1.0.5.dist-info/RECORD
