Metadata-Version: 2.4
Name: nlabapi
Version: 1.0.5
License-File: LICENSE
Home-Page: https://www.getnlab.com
Requires-Python: >=3.8
